{
  "items": [
    {
      "ticker": "GOOG",
      "name": "Alphabet",
      "status": "holding",
      "portfolios": [
        "전체",
        "AI",
        "빅테크",
        "성장주"
      ],
      "template": "bigtech_ai",
      "profile": "GOOG"
    },
    {
      "ticker": "HOOD",
      "name": "Robinhood",
      "status": "holding",
      "portfolios": [
        "전체",
        "핀테크",
        "크립토",
        "고위험성장"
      ],
      "template": "crypto_fintech",
      "profile": "HOOD"
    },
    {
      "ticker": "COIN",
      "name": "Coinbase",
      "status": "watching",
      "portfolios": [
        "전체",
        "크립토",
        "핀테크",
        "고위험성장"
      ],
      "template": "crypto_fintech",
      "profile": "COIN"
    },
    {
      "ticker": "NVDA",
      "name": "NVIDIA",
      "status": "holding",
      "portfolios": [
        "전체",
        "AI",
        "반도체",
        "성장주"
      ],
      "template": "ai_semiconductors",
      "profile": "NVDA"
    },
    {
      "ticker": "LLY",
      "name": "Eli Lilly",
      "status": "holding",
      "portfolios": [
        "전체",
        "헬스케어",
        "비만치료제",
        "성장주"
      ],
      "template": "glp1_pharma",
      "profile": "LLY"
    },
    {
      "ticker": "TTWO",
      "name": "Take-Two Interactive",
      "status": "holding",
      "portfolios": [
        "전체",
        "게임",
        "미디어",
        "성장주"
      ],
      "profile": "TTWO"
    },
    {
      "ticker": "S",
      "name": "SentinelOne",
      "status": "holding",
      "portfolios": [
        "전체",
        "사이버보안",
        "AI",
        "성장주"
      ],
      "profile": "S"
    },
    {
      "ticker": "META",
      "name": "Meta Platforms",
      "status": "holding",
      "portfolios": [
        "전체",
        "AI",
        "빅테크",
        "광고",
        "성장주"
      ],
      "profile": "META"
    },
    {
      "ticker": "FAS",
      "name": "Direxion Daily Financial Bull 3X Shares",
      "status": "holding",
      "portfolios": [
        "전체",
        "ETF",
        "금융",
        "레버리지"
      ],
      "profile": "FAS"
    },
    {
      "ticker": "CURE",
      "name": "Direxion Daily Healthcare Bull 3X Shares",
      "status": "holding",
      "portfolios": [
        "전체",
        "ETF",
        "헬스케어",
        "레버리지"
      ],
      "profile": "CURE"
    },
    {
      "ticker": "OPEN",
      "name": "Opendoor Technologies",
      "status": "holding",
      "portfolios": [
        "전체",
        "부동산",
        "고위험성장"
      ],
      "profile": "OPEN"
    },
    {
      "ticker": "O",
      "name": "Realty Income",
      "status": "holding",
      "portfolios": [
        "전체",
        "리츠",
        "배당",
        "방어주"
      ],
      "profile": "O"
    },
    {
      "ticker": "KO",
      "name": "Coca-Cola",
      "status": "holding",
      "portfolios": [
        "전체",
        "소비재",
        "배당",
        "방어주"
      ],
      "profile": "KO"
    }
  ]
}
